[
  {
    "id": "1",
    "statut": "0",
    "freeze": "1",
    "id_customer": "121",
    "id_product_family": "3",
    "id_product_subfamily": "3",
    "id_factory": null,
    "id_country": "247",
    "id_society": "1",
    "id_productstatus": "3",
    "ref": "2152224395",
    "designation": "FAISCEAU ELEC BBY D22 (HSR25507)",
    "commande_ouverte": "",
    "price_without_cu": "1.57482",
    "price": "1.51000",
    "transfert_price_work": "0.40000",
    "transfert_price_supplies": "0.01000",
    "weight": "13.00",
    "indice": "02",
    "indice_interne": "2",
    "id_product_child": "2",
    "gestion_cu": "0",
    "qtcu": "3.552",
    "id_customcode": "3",
    "date_expiration": "0000-00-00",
    "conditionnement": "500",
    "typeconditionnement": "carton A13",
    "min_prod_quantity": "5000",
    "stock_minimum": "15000",
    "production_delay": "10",
    "livraison_minimum": "0",
    "volume_previsionnel": "180000",
    "id_incoterms": "7",
    "info_public": "",
    "is_prototype": "0",
    "c_200": "1",
    "c_300": "0",
    "c_600": "0",
    "c_700": "0",
    "c_800": "0",
    "date_creation": "0000-00-00 00:00:00",
    "date_modification": "2018-08-15 14:57:20",
    "id_user_creation": null,
    "id_user_modification": "56",
    "price_old": "1.59370",
    "temps_auto": "0",
    "temps_manu": "0"
  },
  {
    "id": "2",
    "statut": "0",
    "freeze": "1",
    "id_customer": "121",
    "id_product_family": "3",
    "id_product_subfamily": "3",
    "id_factory": null,
    "id_country": "247",
    "id_society": "1",
    "id_productstatus": "3",
    "ref": "2265465423289",
    "designation": "HEATING WIRE (HSR25431)",
    "commande_ouverte": "",
    "price_without_cu": "3.13418",
    "price": "3.03000",
    "transfert_price_work": "0.37500",
    "transfert_price_supplies": "0.07423",
    "weight": "21.00",
    "indice": "02",
    "indice_interne": "1",
    "id_product_child": "0",
    "gestion_cu": "0",
    "qtcu": "3.916",
    "id_customcode": "3",
    "date_expiration": "0000-00-00",
    "conditionnement": "150",
    "typeconditionnement": "carton C12",
    "min_prod_quantity": "300",
    "stock_minimum": "0",
    "production_delay": "10",
    "livraison_minimum": "0",
    "volume_previsionnel": "3500",
    "id_incoterms": "7",
    "info_public": "",
    "is_prototype": "0",
    "c_200": "1",
    "c_300": "0",
    "c_600": "0",
    "c_700": "0",
    "c_800": "0",
    "date_creation": "0000-00-00 00:00:00",
    "date_modification": "2018-02-21 10:07:40",
    "id_user_creation": null,
    "id_user_modification": "28",
    "price_old": "3.15500",
    "temps_auto": "0",
    "temps_manu": "0"
  },
  {
    "id": "3",
    "statut": "0",
    "freeze": "1",
    "id_customer": "121",
    "id_product_family": "3",
    "id_product_subfamily": "3",
    "id_factory": null,
    "id_country": "247",
    "id_society": "1",
    "id_productstatus": "3",
    "ref": "22328284370",
    "designation": "HEATING WIRE WITH THERMOSTAT (HSR25470)",
    "commande_ouverte": "",
    "price_without_cu": "4.28129",
    "price": "4.20000",
    "transfert_price_work": "0.40000",
    "transfert_price_supplies": "0.09097",
    "weight": "50.00",
    "indice": "01",
    "indice_interne": "1",
    "id_product_child": "0",
    "gestion_cu": "0",
    "qtcu": "18.568",
    "id_customcode": "3",
    "date_expiration": "0000-00-00",
    "conditionnement": "150",
    "typeconditionnement": "carton C12",
    "min_prod_quantity": "250",
    "stock_minimum": "0",
    "production_delay": "10",
    "livraison_minimum": "0",
    "volume_previsionnel": "1000",
    "id_incoterms": "7",
    "info_public": "",
    "is_prototype": "0",
    "c_200": "1",
    "c_300": "1",
    "c_600": "0",
    "c_700": "0",
    "c_800": "0",
    "date_creation": "0000-00-00 00:00:00",
    "date_modification": "2018-02-21 10:07:08",
    "id_user_creation": null,
    "id_user_modification": "28",
    "price_old": "4.38000",
    "temps_auto": "0",
    "temps_manu": "0"
  },
  {
    "id": "4",
    "statut": "0",
    "freeze": "1",
    "id_customer": "121",
    "id_product_family": "3",
    "id_product_subfamily": "3",
    "id_factory": null,
    "id_country": "247",
    "id_society": "1",
    "id_productstatus": "3",
    "ref": "222686846689",
    "designation": "HEATING WIRE WITH THERMOSTAT- 1 CONNECTOR (HSR25139)",
    "commande_ouverte": "",
    "price_without_cu": "3.44040",
    "price": "3.53400",
    "transfert_price_work": "0.37000",
    "transfert_price_supplies": "0.09097",
    "weight": "49.00",
    "indice": "09",
    "indice_interne": "1",
    "id_product_child": "0",
    "gestion_cu": "0",
    "qtcu": "17.608",
    "id_customcode": "3",
    "date_expiration": "0000-00-00",
    "conditionnement": "150",
    "typeconditionnement": "carton C12",
    "min_prod_quantity": "1000",
    "stock_minimum": "0",
    "production_delay": "10",
    "livraison_minimum": "0",
    "volume_previsionnel": "2000",
    "id_incoterms": "7",
    "info_public": "",
    "is_prototype": "0",
    "c_200": "1",
    "c_300": "1",
    "c_600": "0",
    "c_700": "0",
    "c_800": "0",
    "date_creation": "0000-00-00 00:00:00",
    "date_modification": "2019-01-08 10:34:17",
    "id_user_creation": null,
    "id_user_modification": "37",
    "price_old": "3.53400",
    "temps_auto": "0",
    "temps_manu": "0"
  },
  {
    "id": "5",
    "statut": "0",
    "freeze": "1",
    "id_customer": "121",
    "id_product_family": "3",
    "id_product_subfamily": "3",
    "id_factory": null,
    "id_country": "247",
    "id_society": "1",
    "id_productstatus": "3",
    "ref": "22426564654644",
    "designation": "WIRE HARNESS FOR HEATING QC (HSR25693)",
    "commande_ouverte": "",
    "price_without_cu": "2.36326",
    "price": "2.35000",
    "transfert_price_work": "0.35000",
    "transfert_price_supplies": "0.01000",
    "weight": "20.00",
    "indice": "03",
    "indice_interne": "1",
    "id_product_child": "0",
    "gestion_cu": "0",
    "qtcu": "6.912",
    "id_customcode": "3",
    "date_expiration": "0000-00-00",
    "conditionnement": "300",
    "typeconditionnement": "carton c12",
    "min_prod_quantity": "500",
    "stock_minimum": "0",
    "production_delay": "10",
    "livraison_minimum": "0",
    "volume_previsionnel": "1500",
    "id_incoterms": "7",
    "info_public": "",
    "is_prototype": "0",
    "c_200": "1",
    "c_300": "0",
    "c_600": "0",
    "c_700": "0",
    "c_800": "0",
    "date_creation": "0000-00-00 00:00:00",
    "date_modification": "2018-11-09 16:50:17",
    "id_user_creation": null,
    "id_user_modification": "36",
    "price_old": "2.40000",
    "temps_auto": "0",
    "temps_manu": "0"
  },
  {
    "id": "6",
    "statut": "0",
    "freeze": "1",
    "id_customer": "121",
    "id_product_family": "3",
    "id_product_subfamily": "3",
    "id_factory": null,
    "id_country": "247",
    "id_society": "1",
    "id_productstatus": "3",
    "ref": "222876742942",
    "designation": "HEATING WIRE (HSR25304)",
    "commande_ouverte": "",
    "price_without_cu": "5.50086",
    "price": "5.63000",
    "transfert_price_work": "0.37500",
    "transfert_price_supplies": "0.11401",
    "weight": "50.00",
    "indice": "03",
    "indice_interne": "1",
    "id_product_child": "0",
    "gestion_cu": "0",
    "qtcu": "24.292",
    "id_customcode": "3",
    "date_expiration": "0000-00-00",
    "conditionnement": "150",
    "typeconditionnement": "Carton C12",
    "min_prod_quantity": "150",
    "stock_minimum": "0",
    "production_delay": "10",
    "livraison_minimum": "0",
    "volume_previsionnel": "1500",
    "id_incoterms": "7",
    "info_public": "",
    "is_prototype": "0",
    "c_200": "1",
    "c_300": "1",
    "c_600": "0",
    "c_700": "0",
    "c_800": "0",
    "date_creation": "0000-00-00 00:00:00",
    "date_modification": "2018-08-29 13:28:31",
    "id_user_creation": null,
    "id_user_modification": "26",
    "price_old": "5.63000",
    "temps_auto": "0",
    "temps_manu": "0"
  },
  {
    "id": "7",
    "statut": "0",
    "freeze": "1",
    "id_customer": "121",
    "id_product_family": "3",
    "id_product_subfamily": "3",
    "id_factory": null,
    "id_country": "247",
    "id_society": "1",
    "id_productstatus": "3",
    "ref": "222668745690",
    "designation": "FAISCEAU ELEC RECHAUF( HSR25140 )",
    "commande_ouverte": "",
    "price_without_cu": "4.41706",
    "price": "4.52200",
    "transfert_price_work": "0.37000",
    "transfert_price_supplies": "0.09655",
    "weight": "50.00",
    "indice": "07",
    "indice_interne": "1",
    "id_product_child": "0",
    "gestion_cu": "0",
    "qtcu": "19.740",
    "id_customcode": "3",
    "date_expiration": "0000-00-00",
    "conditionnement": "150",
    "typeconditionnement": "carton C12",
    "min_prod_quantity": "150",
    "stock_minimum": "0",
    "production_delay": "10",
    "livraison_minimum": "0",
    "volume_previsionnel": "1700",
    "id_incoterms": "7",
    "info_public": "",
    "is_prototype": "0",
    "c_200": "1",
    "c_300": "1",
    "c_600": "0",
    "c_700": "0",
    "c_800": "0",
    "date_creation": "0000-00-00 00:00:00",
    "date_modification": "2017-11-02 10:05:39",
    "id_user_creation": null,
    "id_user_modification": "36",
    "price_old": "4.52200",
    "temps_auto": "0",
    "temps_manu": "0"
  },
  {
    "id": "8",
    "statut": "0",
    "freeze": "1",
    "id_customer": "121",
    "id_product_family": "3",
    "id_product_subfamily": "3",
    "id_factory": null,
    "id_country": "247",
    "id_society": "1",
    "id_productstatus": "3",
    "ref": "21768764645739",
    "designation": "WIRE HARNESS FOR HEATING QC (HSR22909)",
    "commande_ouverte": "",
    "price_without_cu": "1.06856",
    "price": "1.07000",
    "transfert_price_work": "0.19000",
    "transfert_price_supplies": "0.01000",
    "weight": "14.00",
    "indice": "05",
    "indice_interne": "1",
    "id_product_child": "0",
    "gestion_cu": "0",
    "qtcu": "5.568",
    "id_customcode": "3",
    "date_expiration": "0000-00-00",
    "conditionnement": "500",
    "typeconditionnement": "carton a13",
    "min_prod_quantity": "1000",
    "stock_minimum": "0",
    "production_delay": "10",
    "livraison_minimum": "0",
    "volume_previsionnel": "0",
    "id_incoterms": "0",
    "info_public": "",
    "is_prototype": "0",
    "c_200": "1",
    "c_300": "0",
    "c_600": "0",
    "c_700": "0",
    "c_800": "0",
    "date_creation": "0000-00-00 00:00:00",
    "date_modification": "2018-03-02 12:05:28",
    "id_user_creation": null,
    "id_user_modification": "60",
    "price_old": "1.09600",
    "temps_auto": "0",
    "temps_manu": "0"
  },
  {
    "id": "9",
    "statut": "0",
    "freeze": "1",
    "id_customer": "121",
    "id_product_family": "3",
    "id_product_subfamily": "3",
    "id_factory": null,
    "id_country": "247",
    "id_society": "1",
    "id_productstatus": "3",
    "ref": "21766565742",
    "designation": "HEATING WIRE WITH THERMOSTAT-1 CONNECTOR (HSR23205)",
    "commande_ouverte": "",
    "price_without_cu": "998.95695",
    "price": "4.19400",
    "transfert_price_work": "0.39000",
    "transfert_price_supplies": "0.12088",
    "weight": "31.00",
    "indice": "06",
    "indice_interne": "1",
    "id_product_child": "0",
    "gestion_cu": "0",
    "qtcu": "8.099",
    "id_customcode": "0",
    "date_expiration": "0000-00-00",
    "conditionnement": "",
    "typeconditionnement": "carton",
    "min_prod_quantity": "500",
    "stock_minimum": "0",
    "production_delay": "10",
    "livraison_minimum": "0",
    "volume_previsionnel": "0",
    "id_incoterms": "0",
    "info_public": "",
    "is_prototype": "0",
    "c_200": "1",
    "c_300": "1",
    "c_600": "0",
    "c_700": "0",
    "c_800": "0",
    "date_creation": "0000-00-00 00:00:00",
    "date_modification": "2017-10-09 12:45:37",
    "id_user_creation": null,
    "id_user_modification": "6",
    "price_old": "999.00000",
    "temps_auto": "0",
    "temps_manu": "0"
  },
  {
    "id": "10",
    "statut": "0",
    "freeze": "1",
    "id_customer": "125",
    "id_product_family": "3",
    "id_product_subfamily": "3",
    "id_factory": null,
    "id_country": "247",
    "id_society": "1",
    "id_productstatus": "3",
    "ref": "S80655600377",
    "designation": "SCR CONNECTOR WIRE (HSR24090)",
    "commande_ouverte": "",
    "price_without_cu": "0.94775",
    "price": "0.98500",
    "transfert_price_work": "0.03800",
    "transfert_price_supplies": "0.01000",
    "weight": "8.35",
    "indice": "00",
    "indice_interne": "1",
    "id_product_child": "0",
    "gestion_cu": "0",
    "qtcu": "7.008",
    "id_customcode": "3",
    "date_expiration": "0000-00-00",
    "conditionnement": "1000",
    "typeconditionnement": "Carton",
    "min_prod_quantity": "1000",
    "stock_minimum": "0",
    "production_delay": "10",
    "livraison_minimum": "0",
    "volume_previsionnel": "0",
    "id_incoterms": "7",
    "info_public": "",
    "is_prototype": "0",
    "c_200": "1",
    "c_300": "1",
    "c_600": "0",
    "c_700": "0",
    "c_800": "0",
    "date_creation": "0000-00-00 00:00:00",
    "date_modification": "2017-09-13 15:32:52",
    "id_user_creation": null,
    "id_user_modification": "49",
    "price_old": "0.98500",
    "temps_auto": "0",
    "temps_manu": "0"
  },
  {
    "id": "11",
    "statut": "0",
    "freeze": "1",
    "id_customer": "125",
    "id_product_family": "3",
    "id_product_subfamily": "3",
    "id_factory": null,
    "id_country": "247",
    "id_society": "1",
    "id_productstatus": "3",
    "ref": "S800066868353386",
    "designation": "SCR CONNECTOR WIRE (HSR 24097)",
    "commande_ouverte": "",
    "price_without_cu": "0.44362",
    "price": "0.43000",
    "transfert_price_work": "0.04200",
    "transfert_price_supplies": "0.01000",
    "weight": "2.00",
    "indice": "03",
    "indice_interne": "1",
    "id_product_child": "777",
    "gestion_cu": "0",
    "qtcu": "1.200",
    "id_customcode": "3",
    "date_expiration": "0000-00-00",
    "conditionnement": "2000",
    "typeconditionnement": "Carton A13",
    "min_prod_quantity": "4000",
    "stock_minimum": "6000",
    "production_delay": "10",
    "livraison_minimum": "0",
    "volume_previsionnel": "66000",
    "id_incoterms": "7",
    "info_public": "",
    "is_prototype": "0",
    "c_200": "1",
    "c_300": "1",
    "c_600": "0",
    "c_700": "0",
    "c_800": "0",
    "date_creation": "0000-00-00 00:00:00",
    "date_modification": "2018-02-21 10:10:05",
    "id_user_creation": null,
    "id_user_modification": "28",
    "price_old": "0.45000",
    "temps_auto": "0",
    "temps_manu": "0"
  },
  {
    "id": "12",
    "statut": "0",
    "freeze": "1",
    "id_customer": "125",
    "id_product_family": "3",
    "id_product_subfamily": "3",
    "id_factory": null,
    "id_country": "247",
    "id_society": "1",
    "id_productstatus": "3",
    "ref": "S8000333",
    "designation": "ELECTRIC WIRE  165MM (HSR23856 \/ 219832)",
    "commande_ouverte": "",
    "price_without_cu": "0.46260",
    "price": "0.46000",
    "transfert_price_work": "0.03800",
    "transfert_price_supplies": "0.01000",
    "weight": "2.50",
    "indice": "04",
    "indice_interne": "1",
    "id_product_child": "0",
    "gestion_cu": "0",
    "qtcu": "1.392",
    "id_customcode": "3",
    "date_expiration": "0000-00-00",
    "conditionnement": "4000",
    "typeconditionnement": "Carton A13",
    "min_prod_quantity": "1000",
    "stock_minimum": "0",
    "production_delay": "10",
    "livraison_minimum": "0",
    "volume_previsionnel": "90000",
    "id_incoterms": "7",
    "info_public": "",
    "is_prototype": "0",
    "c_200": "1",
    "c_300": "1",
    "c_600": "0",
    "c_700": "0",
    "c_800": "0",
    "date_creation": "0000-00-00 00:00:00",
    "date_modification": "2018-02-21 10:09:42",
    "id_user_creation": null,
    "id_user_modification": "28",
    "price_old": "0.47000",
    "temps_auto": "0",
    "temps_manu": "0"
  },
  {
    "id": "13",
    "statut": "1",
    "freeze": "0",
    "id_customer": "121",
    "id_product_family": "3",
    "id_product_subfamily": "3",
    "id_factory": null,
    "id_country": "247",
    "id_society": "1",
    "id_productstatus": "3",
    "ref": "217740",
    "designation": "WIRE HARNESS FOR HEATING QC (HSR23054)",
    "commande_ouverte": "",
    "price_without_cu": "0.00000",
    "price": "0.00000",
    "transfert_price_work": "99.00000",
    "transfert_price_supplies": "0.05110",
    "weight": "14.00",
    "indice": "02",
    "indice_interne": "1",
    "id_product_child": "0",
    "gestion_cu": "0",
    "qtcu": "4.539",
    "id_customcode": "0",
    "date_expiration": "0000-00-00",
    "conditionnement": "",
    "typeconditionnement": "Carton",
    "min_prod_quantity": "500",
    "stock_minimum": "0",
    "production_delay": "10",
    "livraison_minimum": "0",
    "volume_previsionnel": "0",
    "id_incoterms": "0",
    "info_public": "",
    "is_prototype": "0",
    "c_200": "1",
    "c_300": "0",
    "c_600": "0",
    "c_700": "0",
    "c_800": "0",
    "date_creation": "0000-00-00 00:00:00",
    "date_modification": "2017-09-13 15:32:19",
    "id_user_creation": null,
    "id_user_modification": "49",
    "price_old": "999.00000",
    "temps_auto": "0",
    "temps_manu": "0"
  },
  {
    "id": "14",
    "statut": "0",
    "freeze": "1",
    "id_customer": "125",
    "id_product_family": "3",
    "id_product_subfamily": "3",
    "id_factory": null,
    "id_country": "247",
    "id_society": "1",
    "id_productstatus": "3",
    "ref": "S8032335700341",
    "designation": "ELECTRIC WIRE 620MM (HSR23916 \/ 219836)",
    "commande_ouverte": "",
    "price_without_cu": "0.84938",
    "price": "0.88000",
    "transfert_price_work": "0.03750",
    "transfert_price_supplies": "0.01000",
    "weight": "0.00",
    "indice": "04",
    "indice_interne": "1",
    "id_product_child": "0",
    "gestion_cu": "0",
    "qtcu": "5.760",
    "id_customcode": "3",
    "date_expiration": "0000-00-00",
    "conditionnement": "500",
    "typeconditionnement": "Carton",
    "min_prod_quantity": "1000",
    "stock_minimum": "0",
    "production_delay": "10",
    "livraison_minimum": "0",
    "volume_previsionnel": "0",
    "id_incoterms": "7",
    "info_public": "",
    "is_prototype": "0",
    "c_200": "1",
    "c_300": "1",
    "c_600": "0",
    "c_700": "0",
    "c_800": "0",
    "date_creation": "0000-00-00 00:00:00",
    "date_modification": "2017-09-13 15:31:46",
    "id_user_creation": null,
    "id_user_modification": "49",
    "price_old": "0.88000",
    "temps_auto": "0",
    "temps_manu": "0"
  },
  {
    "id": "15",
    "statut": "0",
    "freeze": "1",
    "id_customer": "125",
    "id_product_family": "3",
    "id_product_subfamily": "3",
    "id_factory": null,
    "id_country": "247",
    "id_society": "1",
    "id_productstatus": "3",
    "ref": "S80345354300340",
    "designation": "ELECTRIC WIRE 380MM  (HSR23901 \/ 219833)",
    "commande_ouverte": "",
    "price_without_cu": "0.64163",
    "price": "0.63000",
    "transfert_price_work": "0.03800",
    "transfert_price_supplies": "0.01000",
    "weight": "5.00",
    "indice": "03",
    "indice_interne": "1",
    "id_product_child": "0",
    "gestion_cu": "0",
    "qtcu": "3.456",
    "id_customcode": "3",
    "date_expiration": "0000-00-00",
    "conditionnement": "2000",
    "typeconditionnement": "carton A13",
    "min_prod_quantity": "4000",
    "stock_minimum": "6000",
    "production_delay": "10",
    "livraison_minimum": "0",
    "volume_previsionnel": "66000",
    "id_incoterms": "7",
    "info_public": "",
    "is_prototype": "0",
    "c_200": "1",
    "c_300": "1",
    "c_600": "0",
    "c_700": "0",
    "c_800": "0",
    "date_creation": "0000-00-00 00:00:00",
    "date_modification": "2018-02-21 10:09:24",
    "id_user_creation": null,
    "id_user_modification": "28",
    "price_old": "0.66000",
    "temps_auto": "0",
    "temps_manu": "0"
  },
  {
    "id": "16",
    "statut": "1",
    "freeze": "0",
    "id_customer": "121",
    "id_product_family": "3",
    "id_product_subfamily": "3",
    "id_factory": null,
    "id_country": "247",
    "id_society": "1",
    "id_productstatus": "3",
    "ref": "HSR25522",
    "designation": "Harness Wire HSR25522",
    "commande_ouverte": "",
    "price_without_cu": "998.96172",
    "price": "999.00000",
    "transfert_price_work": "99.00000",
    "transfert_price_supplies": "0.01000",
    "weight": "20.00",
    "indice": "01",
    "indice_interne": "1",
    "id_product_child": "0",
    "gestion_cu": "0",
    "qtcu": "7.200",
    "id_customcode": "0",
    "date_expiration": "0000-00-00",
    "conditionnement": "",
    "typeconditionnement": "Carton",
    "min_prod_quantity": "1000",
    "stock_minimum": "0",
    "production_delay": "10",
    "livraison_minimum": "0",
    "volume_previsionnel": "0",
    "id_incoterms": "0",
    "info_public": "",
    "is_prototype": "0",
    "c_200": "1",
    "c_300": "0",
    "c_600": "0",
    "c_700": "0",
    "c_800": "0",
    "date_creation": "0000-00-00 00:00:00",
    "date_modification": "2017-09-13 15:30:48",
    "id_user_creation": null,
    "id_user_modification": "49",
    "price_old": "999.00000",
    "temps_auto": "0",
    "temps_manu": "0"
  },
  {
    "id": "17",
    "statut": "0",
    "freeze": "1",
    "id_customer": "125",
    "id_product_family": "3",
    "id_product_subfamily": "3",
    "id_factory": null,
    "id_country": "247",
    "id_society": "1",
    "id_productstatus": "3",
    "ref": "S8000342",
    "designation": "ELECTRIC WIRE 705MM (HSR23900 \/ 219835)",
    "commande_ouverte": "",
    "price_without_cu": "0.89504",
    "price": "0.93000",
    "transfert_price_work": "0.03800",
    "transfert_price_supplies": "0.01000",
    "weight": "0.00",
    "indice": "03",
    "indice_interne": "1",
    "id_product_child": "0",
    "gestion_cu": "0",
    "qtcu": "6.576",
    "id_customcode": "3",
    "date_expiration": "0000-00-00",
    "conditionnement": "1000",
    "typeconditionnement": "carton",
    "min_prod_quantity": "1000",
    "stock_minimum": "0",
    "production_delay": "10",
    "livraison_minimum": "0",
    "volume_previsionnel": "0",
    "id_incoterms": "7",
    "info_public": "",
    "is_prototype": "0",
    "c_200": "1",
    "c_300": "1",
    "c_600": "0",
    "c_700": "0",
    "c_800": "0",
    "date_creation": "0000-00-00 00:00:00",
    "date_modification": "2017-09-13 15:30:14",
    "id_user_creation": null,
    "id_user_modification": "49",
    "price_old": "0.93000",
    "temps_auto": "0",
    "temps_manu": "0"
  },
  {
    "id": "18",
    "statut": "0",
    "freeze": "1",
    "id_customer": "121",
    "id_product_family": "3",
    "id_product_subfamily": "3",
    "id_factory": null,
    "id_country": "247",
    "id_society": "1",
    "id_productstatus": "3",
    "ref": "222691",
    "designation": "HEATING WIRE WITH THERMOSTAT- 1 CONNECTOR (HSR 25141)",
    "commande_ouverte": "",
    "price_without_cu": "5.16997",
    "price": "5.23000",
    "transfert_price_work": "0.37000",
    "transfert_price_supplies": "0.09655",
    "weight": "37.60",
    "indice": "07",
    "indice_interne": "1",
    "id_product_child": "0",
    "gestion_cu": "0",
    "qtcu": "11.292",
    "id_customcode": "3",
    "date_expiration": "0000-00-00",
    "conditionnement": "150",
    "typeconditionnement": "carton C12",
    "min_prod_quantity": "400",
    "stock_minimum": "0",
    "production_delay": "10",
    "livraison_minimum": "0",
    "volume_previsionnel": "1000",
    "id_incoterms": "7",
    "info_public": "",
    "is_prototype": "0",
    "c_200": "1",
    "c_300": "1",
    "c_600": "0",
    "c_700": "0",
    "c_800": "0",
    "date_creation": "0000-00-00 00:00:00",
    "date_modification": "2017-11-16 13:24:56",
    "id_user_creation": null,
    "id_user_modification": "36",
    "price_old": "5.23000",
    "temps_auto": "0",
    "temps_manu": "0"
  },
  {
    "id": "19",
    "statut": "0",
    "freeze": "1",
    "id_customer": "125",
    "id_product_family": "3",
    "id_product_subfamily": "3",
    "id_factory": null,
    "id_country": "247",
    "id_society": "1",
    "id_productstatus": "3",
    "ref": "S8000339",
    "designation": "ELECTRIC WIRE 285MM (HSR23857 \/ 219834)",
    "commande_ouverte": "",
    "price_without_cu": "0.55548",
    "price": "0.54000",
    "transfert_price_work": "0.03800",
    "transfert_price_supplies": "0.01000",
    "weight": "3.50",
    "indice": "04",
    "indice_interne": "1",
    "id_product_child": "0",
    "gestion_cu": "0",
    "qtcu": "2.544",
    "id_customcode": "3",
    "date_expiration": "0000-00-00",
    "conditionnement": "4000",
    "typeconditionnement": "carton A13",
    "min_prod_quantity": "4000",
    "stock_minimum": "6000",
    "production_delay": "10",
    "livraison_minimum": "0",
    "volume_previsionnel": "66000",
    "id_incoterms": "7",
    "info_public": "",
    "is_prototype": "0",
    "c_200": "1",
    "c_300": "1",
    "c_600": "0",
    "c_700": "0",
    "c_800": "0",
    "date_creation": "0000-00-00 00:00:00",
    "date_modification": "2018-08-15 09:34:37",
    "id_user_creation": null,
    "id_user_modification": "22",
    "price_old": "0.56900",
    "temps_auto": "0",
    "temps_manu": "0"
  },
  {
    "id": "20",
    "statut": "0",
    "freeze": "1",
    "id_customer": "125",
    "id_product_family": "3",
    "id_product_subfamily": "3",
    "id_factory": null,
    "id_country": "247",
    "id_society": "1",
    "id_productstatus": "3",
    "ref": "S8000280",
    "designation": "ELECTRIC WIRE  190MM  (HSR23665 \/ 218752)",
    "commande_ouverte": "",
    "price_without_cu": "0.48032",
    "price": "0.47000",
    "transfert_price_work": "0.03800",
    "transfert_price_supplies": "0.01000",
    "weight": "2.50",
    "indice": "06",
    "indice_interne": "1",
    "id_product_child": "0",
    "gestion_cu": "0",
    "qtcu": "1.632",
    "id_customcode": "3",
    "date_expiration": "0000-00-00",
    "conditionnement": "4000",
    "typeconditionnement": "carton",
    "min_prod_quantity": "1000",
    "stock_minimum": "1000",
    "production_delay": "10",
    "livraison_minimum": "0",
    "volume_previsionnel": "11000",
    "id_incoterms": "7",
    "info_public": "",
    "is_prototype": "0",
    "c_200": "0",
    "c_300": "1",
    "c_600": "0",
    "c_700": "0",
    "c_800": "0",
    "date_creation": "0000-00-00 00:00:00",
    "date_modification": "2018-02-21 10:08:36",
    "id_user_creation": null,
    "id_user_modification": "28",
    "price_old": "0.48900",
    "temps_auto": "0",
    "temps_manu": "0"
  },
  {
    "id": "21",
    "statut": "1",
    "freeze": "0",
    "id_customer": "121",
    "id_product_family": "3",
    "id_product_subfamily": "3",
    "id_factory": null,
    "id_country": "247",
    "id_society": "1",
    "id_productstatus": "3",
    "ref": "HSR25290",
    "designation": "HEATING WIRE WITH THERMOSTAT 1- CONNECTOR",
    "commande_ouverte": "",
    "price_without_cu": "998.88315",
    "price": "999.00000",
    "transfert_price_work": "99.00000",
    "transfert_price_supplies": "0.24257",
    "weight": "0.00",
    "indice": "00",
    "indice_interne": "1",
    "id_product_child": "0",
    "gestion_cu": "0",
    "qtcu": "21.980",
    "id_customcode": "0",
    "date_expiration": "0000-00-00",
    "conditionnement": "",
    "typeconditionnement": "carton",
    "min_prod_quantity": "500",
    "stock_minimum": "0",
    "production_delay": "10",
    "livraison_minimum": "0",
    "volume_previsionnel": "0",
    "id_incoterms": "0",
    "info_public": "",
    "is_prototype": "0",
    "c_200": "1",
    "c_300": "1",
    "c_600": "0",
    "c_700": "0",
    "c_800": "0",
    "date_creation": "0000-00-00 00:00:00",
    "date_modification": "2017-09-13 15:27:44",
    "id_user_creation": null,
    "id_user_modification": "49",
    "price_old": "999.00000",
    "temps_auto": "0",
    "temps_manu": "0"
  },
  {
    "id": "22",
    "statut": "0",
    "freeze": "1",
    "id_customer": "125",
    "id_product_family": "3",
    "id_product_subfamily": "3",
    "id_factory": null,
    "id_country": "247",
    "id_society": "1",
    "id_productstatus": "3",
    "ref": "S80bfd00598",
    "designation": "SCR CONNECTOR WIRE LENGTH 510MM (HSR 25963)",
    "commande_ouverte": "",
    "price_without_cu": "0.84397",
    "price": "0.87000",
    "transfert_price_work": "0.22500",
    "transfert_price_supplies": "0.01000",
    "weight": "6.15",
    "indice": "00",
    "indice_interne": "1",
    "id_product_child": "0",
    "gestion_cu": "0",
    "qtcu": "4.896",
    "id_customcode": "3",
    "date_expiration": "0000-00-00",
    "conditionnement": "500",
    "typeconditionnement": "A13",
    "min_prod_quantity": "1000",
    "stock_minimum": "0",
    "production_delay": "10",
    "livraison_minimum": "0",
    "volume_previsionnel": "0",
    "id_incoterms": "7",
    "info_public": "",
    "is_prototype": "0",
    "c_200": "1",
    "c_300": "1",
    "c_600": "0",
    "c_700": "0",
    "c_800": "0",
    "date_creation": "0000-00-00 00:00:00",
    "date_modification": "2018-02-27 07:21:34",
    "id_user_creation": null,
    "id_user_modification": "26",
    "price_old": "0.87000",
    "temps_auto": "0",
    "temps_manu": "0"
  },
  {
    "id": "23",
    "statut": "0",
    "freeze": "1",
    "id_customer": "121",
    "id_product_family": "3",
    "id_product_subfamily": "3",
    "id_factory": null,
    "id_country": "247",
    "id_society": "1",
    "id_productstatus": "3",
    "ref": "2229fr06",
    "designation": "HEATING WIRE WITH THERMOSTAT - 1 CONNECTOR (HSR25236)",
    "commande_ouverte": "",
    "price_without_cu": "6.35174",
    "price": "6.25000",
    "transfert_price_work": "0.72200",
    "transfert_price_supplies": "0.15540",
    "weight": "43.00",
    "indice": "01",
    "indice_interne": "1",
    "id_product_child": "0",
    "gestion_cu": "0",
    "qtcu": "16.603",
    "id_customcode": "3",
    "date_expiration": "0000-00-00",
    "conditionnement": "150",
    "typeconditionnement": "carton C12",
    "min_prod_quantity": "500",
    "stock_minimum": "0",
    "production_delay": "10",
    "livraison_minimum": "0",
    "volume_previsionnel": "1500",
    "id_incoterms": "7",
    "info_public": "",
    "is_prototype": "0",
    "c_200": "1",
    "c_300": "1",
    "c_600": "0",
    "c_700": "0",
    "c_800": "0",
    "date_creation": "0000-00-00 00:00:00",
    "date_modification": "2018-02-21 10:04:57",
    "id_user_creation": null,
    "id_user_modification": "28",
    "price_old": "6.44000",
    "temps_auto": "0",
    "temps_manu": "0"
  },
  {
    "id": "24",
    "statut": "0",
    "freeze": "1",
    "id_customer": "121",
    "id_product_family": "3",
    "id_product_subfamily": "3",
    "id_factory": null,
    "id_country": "247",
    "id_society": "1",
    "id_productstatus": "3",
    "ref": "217gt085",
    "designation": "Heating wire with thermostat-PUMA (HSR22941)",
    "commande_ouverte": "",
    "price_without_cu": "4.00798",
    "price": "3.91000",
    "transfert_price_work": "0.35250",
    "transfert_price_supplies": "0.09557",
    "weight": "30.00",
    "indice": "07",
    "indice_interne": "1",
    "id_product_child": "0",
    "gestion_cu": "0",
    "qtcu": "4.895",
    "id_customcode": "3",
    "date_expiration": "0000-00-00",
    "conditionnement": "100",
    "typeconditionnement": "Carton C12",
    "min_prod_quantity": "2000",
    "stock_minimum": "0",
    "production_delay": "10",
    "livraison_minimum": "0",
    "volume_previsionnel": "16000",
    "id_incoterms": "7",
    "info_public": "",
    "is_prototype": "0",
    "c_200": "1",
    "c_300": "1",
    "c_600": "0",
    "c_700": "0",
    "c_800": "0",
    "date_creation": "0000-00-00 00:00:00",
    "date_modification": "2018-02-21 10:04:30",
    "id_user_creation": null,
    "id_user_modification": "28",
    "price_old": "4.03400",
    "temps_auto": "0",
    "temps_manu": "0"
  },
  {
    "id": "25",
    "statut": "0",
    "freeze": "1",
    "id_customer": "125",
    "id_product_family": "3",
    "id_product_subfamily": "3",
    "id_factory": null,
    "id_country": "247",
    "id_society": "1",
    "id_productstatus": "3",
    "ref": "S8000597",
    "designation": "SCR CONNECTOR WIRE LENGTH 310MM (HSR25962)",
    "commande_ouverte": "",
    "price_without_cu": "0.97418",
    "price": "0.99000",
    "transfert_price_work": "0.22500",
    "transfert_price_supplies": "0.01000",
    "weight": "4.00",
    "indice": "00",
    "indice_interne": "1",
    "id_product_child": "0",
    "gestion_cu": "0",
    "qtcu": "2.976",
    "id_customcode": "3",
    "date_expiration": "0000-00-00",
    "conditionnement": "500",
    "typeconditionnement": "carton",
    "min_prod_quantity": "1000",
    "stock_minimum": "0",
    "production_delay": "10",
    "livraison_minimum": "0",
    "volume_previsionnel": "0",
    "id_incoterms": "7",
    "info_public": "",
    "is_prototype": "0",
    "c_200": "1",
    "c_300": "1",
    "c_600": "0",
    "c_700": "0",
    "c_800": "0",
    "date_creation": "0000-00-00 00:00:00",
    "date_modification": "2018-04-25 14:16:24",
    "id_user_creation": null,
    "id_user_modification": "67",
    "price_old": "0.99000",
    "temps_auto": "0",
    "temps_manu": "0"
  },
  {
    "id": "26",
    "statut": "0",
    "freeze": "1",
    "id_customer": "121",
    "id_product_family": "3",
    "id_product_subfamily": "3",
    "id_factory": null,
    "id_country": "247",
    "id_society": "1",
    "id_productstatus": "3",
    "ref": "222905",
    "designation": "HEATING WIRE WITH THERMOSTAT- 1 CONNECTOR (HSR25234)",
    "commande_ouverte": "",
    "price_without_cu": "998.91595",
    "price": "6.00000",
    "transfert_price_work": "0.72200",
    "transfert_price_supplies": "0.14703",
    "weight": "48.00",
    "indice": "01",
    "indice_interne": "1",
    "id_product_child": "0",
    "gestion_cu": "0",
    "qtcu": "15.810",
    "id_customcode": "3",
    "date_expiration": "0000-00-00",
    "conditionnement": "150",
    "typeconditionnement": "carton",
    "min_prod_quantity": "500",
    "stock_minimum": "0",
    "production_delay": "10",
    "livraison_minimum": "150",
    "volume_previsionnel": "4000",
    "id_incoterms": "7",
    "info_public": "",
    "is_prototype": "0",
    "c_200": "1",
    "c_300": "1",
    "c_600": "0",
    "c_700": "0",
    "c_800": "0",
    "date_creation": "0000-00-00 00:00:00",
    "date_modification": "2018-02-21 10:04:02",
    "id_user_creation": null,
    "id_user_modification": "28",
    "price_old": "999.00000",
    "temps_auto": "0",
    "temps_manu": "0"
  },
  {
    "id": "27",
    "statut": "0",
    "freeze": "1",
    "id_customer": "122",
    "id_product_family": "2",
    "id_product_subfamily": "1",
    "id_factory": null,
    "id_country": "247",
    "id_society": "1",
    "id_productstatus": "3",
    "ref": "173bfdnbv3075X",
    "designation": "P84 FAISCEAU PCAR AB  (9819073580 )",
    "commande_ouverte": "Cde 4600003776 SA 5500433366",
    "price_without_cu": "4.46795",
    "price": "4.39700",
    "transfert_price_work": "0.74000",
    "transfert_price_supplies": "0.28547",
    "weight": "160.00",
    "indice": "OR",
    "indice_interne": "2",
    "id_product_child": "0",
    "gestion_cu": "0",
    "qtcu": "22.356",
    "id_customcode": "3",
    "date_expiration": "0000-00-00",
    "conditionnement": "10",
    "typeconditionnement": "Bac Gris",
    "min_prod_quantity": "1000",
    "stock_minimum": "0",
    "production_delay": "10",
    "livraison_minimum": "0",
    "volume_previsionnel": "500",
    "id_incoterms": "1",
    "info_public": "",
    "is_prototype": "0",
    "c_200": "1",
    "c_300": "1",
    "c_600": "0",
    "c_700": "0",
    "c_800": "0",
    "date_creation": "0000-00-00 00:00:00",
    "date_modification": "2019-01-29 12:36:15",
    "id_user_creation": null,
    "id_user_modification": "28",
    "price_old": "4.58800",
    "temps_auto": "0",
    "temps_manu": "0"
  },
  {
    "id": "28",
    "statut": "0",
    "freeze": "1",
    "id_customer": "124",
    "id_product_family": "2",
    "id_product_subfamily": "1",
    "id_factory": null,
    "id_country": "247",
    "id_society": "1",
    "id_productstatus": "3",
    "ref": "1594hy053X",
    "designation": "K0  FAISCEAU PCAV SAM DRL",
    "commande_ouverte": "Cde 4600034568 SA 5500486829",
    "price_without_cu": "14.82366",
    "price": "14.41700",
    "transfert_price_work": "2.91500",
    "transfert_price_supplies": "1.75576",
    "weight": "577.00",
    "indice": "01",
    "indice_interne": "2",
    "id_product_child": "0",
    "gestion_cu": "0",
    "qtcu": "153.857",
    "id_customcode": "3",
    "date_expiration": "0000-00-00",
    "conditionnement": "6",
    "typeconditionnement": "Carton C13",
    "min_prod_quantity": "800",
    "stock_minimum": "0",
    "production_delay": "10",
    "livraison_minimum": "0",
    "volume_previsionnel": "46000",
    "id_incoterms": "7",
    "info_public": "",
    "is_prototype": "0",
    "c_200": "1",
    "c_300": "1",
    "c_600": "0",
    "c_700": "0",
    "c_800": "0",
    "date_creation": "0000-00-00 00:00:00",
    "date_modification": "2019-01-29 10:39:32",
    "id_user_creation": null,
    "id_user_modification": "28",
    "price_old": "15.65000",
    "temps_auto": "0",
    "temps_manu": "0"
  },
  {
    "id": "29",
    "statut": "0",
    "freeze": "1",
    "id_customer": "122",
    "id_product_family": "2",
    "id_product_subfamily": "1",
    "id_factory": null,
    "id_country": "247",
    "id_society": "1",
    "id_productstatus": "3",
    "ref": "1733yt114X",
    "designation": "P84 FAISCEAU PCAR AB+AAS (9819073980 )",
    "commande_ouverte": "Cde 4600003776 SA 5500433368",
    "price_without_cu": "8.48876",
    "price": "8.46400",
    "transfert_price_work": "1.53300",
    "transfert_price_supplies": "0.61083",
    "weight": "210.00",
    "indice": "OR",
    "indice_interne": "1",
    "id_product_child": "0",
    "gestion_cu": "0",
    "qtcu": "58.891",
    "id_customcode": "3",
    "date_expiration": "0000-00-00",
    "conditionnement": "10",
    "typeconditionnement": "Bac Gris",
    "min_prod_quantity": "1500",
    "stock_minimum": "0",
    "production_delay": "10",
    "livraison_minimum": "0",
    "volume_previsionnel": "0",
    "id_incoterms": "1",
    "info_public": "",
    "is_prototype": "0",
    "c_200": "1",
    "c_300": "1",
    "c_600": "0",
    "c_700": "0",
    "c_800": "0",
    "date_creation": "0000-00-00 00:00:00",
    "date_modification": "2019-01-29 12:37:36",
    "id_user_creation": null,
    "id_user_modification": "28",
    "price_old": "8.80500",
    "temps_auto": "0",
    "temps_manu": "0"
  },
  {
    "id": "30",
    "statut": "0",
    "freeze": "1",
    "id_customer": "122",
    "id_product_family": "2",
    "id_product_subfamily": "1",
    "id_factory": null,
    "id_country": "247",
    "id_society": "1",
    "id_productstatus": "3",
    "ref": "173329ez5X",
    "designation": "P84 FAISCEAU PCAR AB+AAS+ABC  (9819073680 )",
    "commande_ouverte": "Cde 4600003776 SA 5500433370",
    "price_without_cu": "9.54139",
    "price": "9.54700",
    "transfert_price_work": "1.67000",
    "transfert_price_supplies": "0.71980",
    "weight": "242.00",
    "indice": "OR",
    "indice_interne": "2",
    "id_product_child": "0",
    "gestion_cu": "0",
    "qtcu": "71.435",
    "id_customcode": "3",
    "date_expiration": "0000-00-00",
    "conditionnement": "8",
    "typeconditionnement": "Bac Gris",
    "min_prod_quantity": "500",
    "stock_minimum": "0",
    "production_delay": "10",
    "livraison_minimum": "0",
    "volume_previsionnel": "2200",
    "id_incoterms": "1",
    "info_public": "",
    "is_prototype": "0",
    "c_200": "1",
    "c_300": "1",
    "c_600": "0",
    "c_700": "0",
    "c_800": "0",
    "date_creation": "0000-00-00 00:00:00",
    "date_modification": "2019-01-29 12:38:31",
    "id_user_creation": null,
    "id_user_modification": "28",
    "price_old": "9.92500",
    "temps_auto": "0",
    "temps_manu": "0"
  },
  {
    "id": "31",
    "statut": "0",
    "freeze": "1",
    "id_customer": "122",
    "id_product_family": "2",
    "id_product_subfamily": "1",
    "id_factory": null,
    "id_country": "247",
    "id_society": "1",
    "id_productstatus": "3",
    "ref": "182de6568X",
    "designation": "P84 FAISCEAU PCAR AB+ABC  (9819073780 )",
    "commande_ouverte": "Cde 400003776 SA 5500433367",
    "price_without_cu": "6.67413",
    "price": "6.57700",
    "transfert_price_work": "1.08700",
    "transfert_price_supplies": "0.39602",
    "weight": "0.00",
    "indice": "OR",
    "indice_interne": "1",
    "id_product_child": "0",
    "gestion_cu": "0",
    "qtcu": "34.799",
    "id_customcode": "3",
    "date_expiration": "0000-00-00",
    "conditionnement": "10",
    "typeconditionnement": "Bac Gris",
    "min_prod_quantity": "500",
    "stock_minimum": "0",
    "production_delay": "10",
    "livraison_minimum": "0",
    "volume_previsionnel": "500",
    "id_incoterms": "1",
    "info_public": "",
    "is_prototype": "0",
    "c_200": "1",
    "c_300": "1",
    "c_600": "0",
    "c_700": "0",
    "c_800": "0",
    "date_creation": "0000-00-00 00:00:00",
    "date_modification": "2019-01-29 12:36:51",
    "id_user_creation": null,
    "id_user_modification": "28",
    "price_old": "6.86100",
    "temps_auto": "0",
    "temps_manu": "0"
  },
  {
    "id": "32",
    "statut": "0",
    "freeze": "1",
    "id_customer": "130",
    "id_product_family": "2",
    "id_product_subfamily": "1",
    "id_factory": null,
    "id_country": "247",
    "id_society": "1",
    "id_productstatus": "3",
    "ref": "20697",
    "designation": "CABLEADO CAPTORES E3 SA 5500330104",
    "commande_ouverte": "",
    "price_without_cu": "9.22343",
    "price": "9.52500",
    "transfert_price_work": "1.38500",
    "transfert_price_supplies": "0.65679",
    "weight": "209.00",
    "indice": "01",
    "indice_interne": "1",
    "id_product_child": "0",
    "gestion_cu": "0",
    "qtcu": "56.159",
    "id_customcode": "3",
    "date_expiration": "0000-00-00",
    "conditionnement": "25",
    "typeconditionnement": "CARTON C12",
    "min_prod_quantity": "300",
    "stock_minimum": "0",
    "production_delay": "10",
    "livraison_minimum": "0",
    "volume_previsionnel": "14000",
    "id_incoterms": "7",
    "info_public": "",
    "is_prototype": "0",
    "c_200": "1",
    "c_300": "0",
    "c_600": "0",
    "c_700": "0",
    "c_800": "0",
    "date_creation": "0000-00-00 00:00:00",
    "date_modification": "2017-10-06 13:22:32",
    "id_user_creation": null,
    "id_user_modification": "22",
    "price_old": "9.52500",
    "temps_auto": "0",
    "temps_manu": "0"
  },
  {
    "id": "33",
    "statut": "0",
    "freeze": "1",
    "id_customer": "122",
    "id_product_family": "2",
    "id_product_subfamily": "1",
    "id_factory": null,
    "id_country": "247",
    "id_society": "1",
    "id_productstatus": "3",
    "ref": "1676974X",
    "designation": "B8 FAISCEAU PCAV HALO SANS AAS",
    "commande_ouverte": "Cde 4600003776 SA 5500310397",
    "price_without_cu": "4.30793",
    "price": "4.44700",
    "transfert_price_work": "1.09000",
    "transfert_price_supplies": "0.57593",
    "weight": "193.00",
    "indice": "01",
    "indice_interne": "1",
    "id_product_child": "0",
    "gestion_cu": "0",
    "qtcu": "51.037",
    "id_customcode": "3",
    "date_expiration": "0000-00-00",
    "conditionnement": "10",
    "typeconditionnement": "Bac Gris",
    "min_prod_quantity": "100",
    "stock_minimum": "0",
    "production_delay": "10",
    "livraison_minimum": "0",
    "volume_previsionnel": "500",
    "id_incoterms": "1",
    "info_public": "",
    "is_prototype": "0",
    "c_200": "1",
    "c_300": "0",
    "c_600": "0",
    "c_700": "0",
    "c_800": "0",
    "date_creation": "0000-00-00 00:00:00",
    "date_modification": "2019-01-29 12:35:46",
    "id_user_creation": null,
    "id_user_modification": "28",
    "price_old": "4.58200",
    "temps_auto": "0",
    "temps_manu": "0"
  },
  {
    "id": "34",
    "statut": "0",
    "freeze": "1",
    "id_customer": "122",
    "id_product_family": "2",
    "id_product_subfamily": "1",
    "id_factory": null,
    "id_country": "247",
    "id_society": "1",
    "id_productstatus": "3",
    "ref": "1176481X",
    "designation": "T91 FAISCEAU PCAR AAS",
    "commande_ouverte": "Cde 4600003776 SA 5500247837",
    "price_without_cu": "6.13822",
    "price": "6.47300",
    "transfert_price_work": "1.38200",
    "transfert_price_supplies": "0.50061",
    "weight": "170.00",
    "indice": "01",
    "indice_interne": "2",
    "id_product_child": "0",
    "gestion_cu": "0",
    "qtcu": "43.124",
    "id_customcode": "3",
    "date_expiration": "0000-00-00",
    "conditionnement": "10",
    "typeconditionnement": "Bac Gris",
    "min_prod_quantity": "1000",
    "stock_minimum": "0",
    "production_delay": "10",
    "livraison_minimum": "0",
    "volume_previsionnel": "27000",
    "id_incoterms": "7",
    "info_public": "",
    "is_prototype": "0",
    "c_200": "1",
    "c_300": "1",
    "c_600": "0",
    "c_700": "0",
    "c_800": "0",
    "date_creation": "0000-00-00 00:00:00",
    "date_modification": "2019-02-22 06:01:29",
    "id_user_creation": null,
    "id_user_modification": "58",
    "price_old": "6.40500",
    "temps_auto": "0",
    "temps_manu": "0"
  },
  {
    "id": "35",
    "statut": "0",
    "freeze": "1",
    "id_customer": "122",
    "id_product_family": "2",
    "id_product_subfamily": "1",
    "id_factory": null,
    "id_country": "247",
    "id_society": "1",
    "id_productstatus": "3",
    "ref": "1188238X",
    "designation": "A94 FAISCEAU PCAV  CAPTEUR",
    "commande_ouverte": "Cde 4600015003 SA 5500211865",
    "price_without_cu": "8.31429",
    "price": "8.76900",
    "transfert_price_work": "1.76500",
    "transfert_price_supplies": "0.60390",
    "weight": "230.00",
    "indice": "00",
    "indice_interne": "2",
    "id_product_child": "0",
    "gestion_cu": "0",
    "qtcu": "56.511",
    "id_customcode": "3",
    "date_expiration": "0000-00-00",
    "conditionnement": "10",
    "typeconditionnement": "Bac Gris",
    "min_prod_quantity": "500",
    "stock_minimum": "0",
    "production_delay": "10",
    "livraison_minimum": "0",
    "volume_previsionnel": "9000",
    "id_incoterms": "1",
    "info_public": "",
    "is_prototype": "0",
    "c_200": "1",
    "c_300": "1",
    "c_600": "0",
    "c_700": "0",
    "c_800": "0",
    "date_creation": "0000-00-00 00:00:00",
    "date_modification": "2019-01-29 10:38:48",
    "id_user_creation": null,
    "id_user_modification": "28",
    "price_old": "8.67400",
    "temps_auto": "0",
    "temps_manu": "0"
  },
  {
    "id": "36",
    "statut": "0",
    "freeze": "1",
    "id_customer": "122",
    "id_product_family": "2",
    "id_product_subfamily": "1",
    "id_factory": null,
    "id_country": "247",
    "id_society": "1",
    "id_productstatus": "3",
    "ref": "15628147257X",
    "designation": "B8 FAISCEAU PCAV HALO AAS (9809930680)",
    "commande_ouverte": "Cde 4600003776 SA 5500310396",
    "price_without_cu": "8.79491",
    "price": "9.02500",
    "transfert_price_work": "1.72000",
    "transfert_price_supplies": "0.92616",
    "weight": "359.60",
    "indice": "01",
    "indice_interne": "3",
    "id_product_child": "0",
    "gestion_cu": "0",
    "qtcu": "95.512",
    "id_customcode": "3",
    "date_expiration": "0000-00-00",
    "conditionnement": "8",
    "typeconditionnement": "Bac Gris",
    "min_prod_quantity": "200",
    "stock_minimum": "0",
    "production_delay": "10",
    "livraison_minimum": "0",
    "volume_previsionnel": "2000",
    "id_incoterms": "1",
    "info_public": "",
    "is_prototype": "0",
    "c_200": "1",
    "c_300": "0",
    "c_600": "0",
    "c_700": "0",
    "c_800": "0",
    "date_creation": "0000-00-00 00:00:00",
    "date_modification": "2019-01-29 12:34:51",
    "id_user_creation": null,
    "id_user_modification": "28",
    "price_old": "9.29100",
    "temps_auto": "0",
    "temps_manu": "0"
  },
  {
    "id": "37",
    "statut": "0",
    "freeze": "1",
    "id_customer": "122",
    "id_product_family": "2",
    "id_product_subfamily": "1",
    "id_factory": null,
    "id_country": "247",
    "id_society": "1",
    "id_productstatus": "3",
    "ref": "122508040X",
    "designation": "T92 FAISCEAU PCAR AAS (9803265980)",
    "commande_ouverte": "Cde 4600003776 SA 5500288748",
    "price_without_cu": "6.55230",
    "price": "6.99900",
    "transfert_price_work": "2.37250",
    "transfert_price_supplies": "0.51110",
    "weight": "182.00",
    "indice": "01",
    "indice_interne": "2",
    "id_product_child": "0",
    "gestion_cu": "0",
    "qtcu": "46.149",
    "id_customcode": "3",
    "date_expiration": "0000-00-00",
    "conditionnement": "10",
    "typeconditionnement": "BAC  GRIS",
    "min_prod_quantity": "1000",
    "stock_minimum": "0",
    "production_delay": "10",
    "livraison_minimum": "0",
    "volume_previsionnel": "28000",
    "id_incoterms": "7",
    "info_public": "",
    "is_prototype": "0",
    "c_200": "1",
    "c_300": "0",
    "c_600": "0",
    "c_700": "0",
    "c_800": "0",
    "date_creation": "0000-00-00 00:00:00",
    "date_modification": "2019-01-29 12:02:40",
    "id_user_creation": null,
    "id_user_modification": "28",
    "price_old": "6.93500",
    "temps_auto": "0",
    "temps_manu": "0"
  },
  {
    "id": "38",
    "statut": "0",
    "freeze": "1",
    "id_customer": "122",
    "id_product_family": "2",
    "id_product_subfamily": "1",
    "id_factory": null,
    "id_country": "247",
    "id_society": "1",
    "id_productstatus": "3",
    "ref": "124255957X",
    "designation": "T91 FAISCEAU PCAR AAS+SAM",
    "commande_ouverte": "Cde 4600003776 SA 5500247838",
    "price_without_cu": "7.32316",
    "price": "7.81200",
    "transfert_price_work": "1.34900",
    "transfert_price_supplies": "0.66617",
    "weight": "110.00",
    "indice": "01",
    "indice_interne": "2",
    "id_product_child": "0",
    "gestion_cu": "0",
    "qtcu": "63.228",
    "id_customcode": "3",
    "date_expiration": "0000-00-00",
    "conditionnement": "10",
    "typeconditionnement": "Bac Gris",
    "min_prod_quantity": "100",
    "stock_minimum": "0",
    "production_delay": "10",
    "livraison_minimum": "0",
    "volume_previsionnel": "1500",
    "id_incoterms": "1",
    "info_public": "",
    "is_prototype": "0",
    "c_200": "1",
    "c_300": "0",
    "c_600": "0",
    "c_700": "0",
    "c_800": "0",
    "date_creation": "0000-00-00 00:00:00",
    "date_modification": "2019-01-29 11:00:30",
    "id_user_creation": null,
    "id_user_modification": "28",
    "price_old": "7.72000",
    "temps_auto": "0",
    "temps_manu": "0"
  },
  {
    "id": "39",
    "statut": "0",
    "freeze": "1",
    "id_customer": "122",
    "id_product_family": "2",
    "id_product_subfamily": "1",
    "id_factory": null,
    "id_country": "247",
    "id_society": "1",
    "id_productstatus": "3",
    "ref": "124536958X",
    "designation": "T91 FAISCEAU PCAR AAS+ADML",
    "commande_ouverte": "Cde 4600003776 SA 5500247839",
    "price_without_cu": "7.30965",
    "price": "7.78700",
    "transfert_price_work": "1.27900",
    "transfert_price_supplies": "0.61925",
    "weight": "200.00",
    "indice": "01",
    "indice_interne": "2",
    "id_product_child": "0",
    "gestion_cu": "0",
    "qtcu": "54.279",
    "id_customcode": "3",
    "date_expiration": "0000-00-00",
    "conditionnement": "10",
    "typeconditionnement": "Bac Gris",
    "min_prod_quantity": "1000",
    "stock_minimum": "0",
    "production_delay": "10",
    "livraison_minimum": "0",
    "volume_previsionnel": "9000",
    "id_incoterms": "1",
    "info_public": "",
    "is_prototype": "0",
    "c_200": "1",
    "c_300": "0",
    "c_600": "0",
    "c_700": "0",
    "c_800": "0",
    "date_creation": "0000-00-00 00:00:00",
    "date_modification": "2019-01-29 12:02:04",
    "id_user_creation": null,
    "id_user_modification": "28",
    "price_old": "7.69500",
    "temps_auto": "0",
    "temps_manu": "0"
  },
  {
    "id": "40",
    "statut": "0",
    "freeze": "1",
    "id_customer": "122",
    "id_product_family": "2",
    "id_product_subfamily": "1",
    "id_factory": null,
    "id_country": "247",
    "id_society": "1",
    "id_productstatus": "3",
    "ref": "124558961X",
    "designation": "T91 FAISCEAU PCAR AAS+ADML+SAM",
    "commande_ouverte": "Cde 4600003776 SA 5500247836",
    "price_without_cu": "8.87159",
    "price": "9.49100",
    "transfert_price_work": "1.60700",
    "transfert_price_supplies": "0.77407",
    "weight": "255.00",
    "indice": "01",
    "indice_interne": "2",
    "id_product_child": "0",
    "gestion_cu": "0",
    "qtcu": "74.383",
    "id_customcode": "3",
    "date_expiration": "0000-00-00",
    "conditionnement": "10",
    "typeconditionnement": "Bac Gris",
    "min_prod_quantity": "500",
    "stock_minimum": "0",
    "production_delay": "10",
    "livraison_minimum": "0",
    "volume_previsionnel": "7000",
    "id_incoterms": "1",
    "info_public": "",
    "is_prototype": "0",
    "c_200": "1",
    "c_300": "0",
    "c_600": "0",
    "c_700": "0",
    "c_800": "0",
    "date_creation": "0000-00-00 00:00:00",
    "date_modification": "2019-01-29 10:56:04",
    "id_user_creation": null,
    "id_user_modification": "28",
    "price_old": "9.38700",
    "temps_auto": "0",
    "temps_manu": "0"
  },
  {
    "id": "41",
    "statut": "0",
    "freeze": "1",
    "id_customer": "122",
    "id_product_family": "2",
    "id_product_subfamily": "1",
    "id_factory": null,
    "id_country": "247",
    "id_society": "1",
    "id_productstatus": "3",
    "ref": "134718292X",
    "designation": "T92 FAISCEAU PCAR AAS+ADML (9803266080)",
    "commande_ouverte": "Cde 4600003776 SA 5500288749",
    "price_without_cu": "7.04236",
    "price": "7.55900",
    "transfert_price_work": "2.75250",
    "transfert_price_supplies": "0.61119",
    "weight": "209.00",
    "indice": "01",
    "indice_interne": "2",
    "id_product_child": "0",
    "gestion_cu": "0",
    "qtcu": "59.558",
    "id_customcode": "3",
    "date_expiration": "0000-00-00",
    "conditionnement": "10",
    "typeconditionnement": "Bac Gris",
    "min_prod_quantity": "1000",
    "stock_minimum": "0",
    "production_delay": "10",
    "livraison_minimum": "0",
    "volume_previsionnel": "18000",
    "id_incoterms": "1",
    "info_public": "",
    "is_prototype": "0",
    "c_200": "1",
    "c_300": "0",
    "c_600": "0",
    "c_700": "0",
    "c_800": "0",
    "date_creation": "0000-00-00 00:00:00",
    "date_modification": "2019-01-29 12:11:57",
    "id_user_creation": null,
    "id_user_modification": "28",
    "price_old": "7.48100",
    "temps_auto": "0",
    "temps_manu": "0"
  },
  {
    "id": "42",
    "statut": "0",
    "freeze": "1",
    "id_customer": "122",
    "id_product_family": "2",
    "id_product_subfamily": "1",
    "id_factory": null,
    "id_country": "247",
    "id_society": "1",
    "id_productstatus": "3",
    "ref": "131lo870586X",
    "designation": "T92 FAISCEAU PCAR AAS+SAM (9803266180)",
    "commande_ouverte": "Cde 4600003776 SA 5500288750",
    "price_without_cu": "8.18189",
    "price": "8.78000",
    "transfert_price_work": "1.46000",
    "transfert_price_supplies": "0.68797",
    "weight": "242.00",
    "indice": "01",
    "indice_interne": "2",
    "id_product_child": "0",
    "gestion_cu": "0",
    "qtcu": "66.981",
    "id_customcode": "3",
    "date_expiration": "0000-00-00",
    "conditionnement": "10",
    "typeconditionnement": "BAC  GRIS",
    "min_prod_quantity": "100",
    "stock_minimum": "0",
    "production_delay": "10",
    "livraison_minimum": "0",
    "volume_previsionnel": "450",
    "id_incoterms": "1",
    "info_public": "",
    "is_prototype": "0",
    "c_200": "1",
    "c_300": "0",
    "c_600": "0",
    "c_700": "0",
    "c_800": "0",
    "date_creation": "0000-00-00 00:00:00",
    "date_modification": "2019-01-29 12:13:44",
    "id_user_creation": null,
    "id_user_modification": "28",
    "price_old": "8.68300",
    "temps_auto": "0",
    "temps_manu": "0"
  },
  {
    "id": "43",
    "statut": "0",
    "freeze": "1",
    "id_customer": "122",
    "id_product_family": "2",
    "id_product_subfamily": "1",
    "id_factory": null,
    "id_country": "247",
    "id_society": "1",
    "id_productstatus": "3",
    "ref": "1318808X",
    "designation": "T92 FAISCEAU PCAR AAS+SAM+ADML (9803265280)",
    "commande_ouverte": "Cde 4600003776 SA 5500288751",
    "price_without_cu": "8.79032",
    "price": "9.37500",
    "transfert_price_work": "2.22000",
    "transfert_price_supplies": "0.78799",
    "weight": "266.00",
    "indice": "01",
    "indice_interne": "2",
    "id_product_child": "0",
    "gestion_cu": "0",
    "qtcu": "80.367",
    "id_customcode": "3",
    "date_expiration": "0000-00-00",
    "conditionnement": "10",
    "typeconditionnement": "Bac Gris",
    "min_prod_quantity": "500",
    "stock_minimum": "0",
    "production_delay": "10",
    "livraison_minimum": "0",
    "volume_previsionnel": "7000",
    "id_incoterms": "1",
    "info_public": "",
    "is_prototype": "0",
    "c_200": "1",
    "c_300": "0",
    "c_600": "0",
    "c_700": "0",
    "c_800": "0",
    "date_creation": "0000-00-00 00:00:00",
    "date_modification": "2019-01-29 12:14:22",
    "id_user_creation": null,
    "id_user_modification": "28",
    "price_old": "9.26500",
    "temps_auto": "0",
    "temps_manu": "0"
  },
  {
    "id": "44",
    "statut": "0",
    "freeze": "1",
    "id_customer": "122",
    "id_product_family": "2",
    "id_product_subfamily": "1",
    "id_factory": null,
    "id_country": "247",
    "id_society": "1",
    "id_productstatus": "3",
    "ref": "156255276X",
    "designation": "B8 FAISCEAU PCAV HALO AAS SAM (9809930780 )",
    "commande_ouverte": "Cde 4600003776 SA 5500310395",
    "price_without_cu": "11.32654",
    "price": "11.71800",
    "transfert_price_work": "2.06000",
    "transfert_price_supplies": "1.23138",
    "weight": "300.00",
    "indice": "01",
    "indice_interne": "3",
    "id_product_child": "0",
    "gestion_cu": "0",
    "qtcu": "127.250",
    "id_customcode": "3",
    "date_expiration": "0000-00-00",
    "conditionnement": "8",
    "typeconditionnement": "Bac Gris",
    "min_prod_quantity": "24",
    "stock_minimum": "0",
    "production_delay": "10",
    "livraison_minimum": "0",
    "volume_previsionnel": "300",
    "id_incoterms": "1",
    "info_public": "",
    "is_prototype": "0",
    "c_200": "1",
    "c_300": "0",
    "c_600": "0",
    "c_700": "0",
    "c_800": "0",
    "date_creation": "0000-00-00 00:00:00",
    "date_modification": "2019-01-29 12:34:20",
    "id_user_creation": null,
    "id_user_modification": "28",
    "price_old": "12.05900",
    "temps_auto": "0",
    "temps_manu": "0"
  },
  {
    "id": "45",
    "statut": "0",
    "freeze": "1",
    "id_customer": "122",
    "id_product_family": "2",
    "id_product_subfamily": "1",
    "id_factory": null,
    "id_country": "247",
    "id_society": "1",
    "id_productstatus": "3",
    "ref": "1732999X",
    "designation": "P84 FAISCEAU  PCAR AB AAS SAM ABC (9819073980)",
    "commande_ouverte": "Cde 4600003776 SA 5500433371",
    "price_without_cu": "11.53887",
    "price": "11.59200",
    "transfert_price_work": "2.00000",
    "transfert_price_supplies": "0.90995",
    "weight": "310.00",
    "indice": "OR",
    "indice_interne": "2",
    "id_product_child": "0",
    "gestion_cu": "0",
    "qtcu": "93.693",
    "id_customcode": "3",
    "date_expiration": "0000-00-00",
    "conditionnement": "8",
    "typeconditionnement": "Bac Gris",
    "min_prod_quantity": "1000",
    "stock_minimum": "0",
    "production_delay": "10",
    "livraison_minimum": "0",
    "volume_previsionnel": "0",
    "id_incoterms": "1",
    "info_public": "",
    "is_prototype": "0",
    "c_200": "1",
    "c_300": "1",
    "c_600": "0",
    "c_700": "0",
    "c_800": "0",
    "date_creation": "0000-00-00 00:00:00",
    "date_modification": "2019-01-29 12:39:20",
    "id_user_creation": null,
    "id_user_modification": "28",
    "price_old": "12.04200",
    "temps_auto": "0",
    "temps_manu": "0"
  },
  {
    "id": "46",
    "statut": "0",
    "freeze": "1",
    "id_customer": "122",
    "id_product_family": "2",
    "id_product_subfamily": "1",
    "id_factory": null,
    "id_country": "247",
    "id_society": "1",
    "id_productstatus": "3",
    "ref": "167636976X",
    "designation": "B8 FAISCEAU PCAV LAD LED AAS ( 9810220680 )",
    "commande_ouverte": "Cde 4600003776 SA 5500310393",
    "price_without_cu": "9.37452",
    "price": "9.69100",
    "transfert_price_work": "1.89000",
    "transfert_price_supplies": "1.04078",
    "weight": "336.70",
    "indice": "01",
    "indice_interne": "2",
    "id_product_child": "0",
    "gestion_cu": "0",
    "qtcu": "111.635",
    "id_customcode": "3",
    "date_expiration": "0000-00-00",
    "conditionnement": "8",
    "typeconditionnement": "Bac Gris",
    "min_prod_quantity": "50",
    "stock_minimum": "0",
    "production_delay": "10",
    "livraison_minimum": "0",
    "volume_previsionnel": "700",
    "id_incoterms": "1",
    "info_public": "",
    "is_prototype": "2",
    "c_200": "1",
    "c_300": "0",
    "c_600": "0",
    "c_700": "0",
    "c_800": "0",
    "date_creation": "0000-00-00 00:00:00",
    "date_modification": "2019-01-29 12:22:22",
    "id_user_creation": null,
    "id_user_modification": "28",
    "price_old": "9.97400",
    "temps_auto": "0",
    "temps_manu": "0"
  },
  {
    "id": "47",
    "statut": "0",
    "freeze": "1",
    "id_customer": "122",
    "id_product_family": "2",
    "id_product_subfamily": "1",
    "id_factory": null,
    "id_country": "247",
    "id_society": "1",
    "id_productstatus": "3",
    "ref": "167669978X",
    "designation": "B8 FAISCEAU PCAV LAD LED AAS SAM ( 9809930880 )",
    "commande_ouverte": "Cde 4600003776 SA 5500310394",
    "price_without_cu": "11.88539",
    "price": "12.30900",
    "transfert_price_work": "2.50000",
    "transfert_price_supplies": "1.32139",
    "weight": "460.00",
    "indice": "01",
    "indice_interne": "3",
    "id_product_child": "0",
    "gestion_cu": "0",
    "qtcu": "140.469",
    "id_customcode": "3",
    "date_expiration": "0000-00-00",
    "conditionnement": "8",
    "typeconditionnement": "Bac Gris",
    "min_prod_quantity": "1000",
    "stock_minimum": "0",
    "production_delay": "10",
    "livraison_minimum": "0",
    "volume_previsionnel": "1800",
    "id_incoterms": "1",
    "info_public": "",
    "is_prototype": "1",
    "c_200": "1",
    "c_300": "0",
    "c_600": "0",
    "c_700": "0",
    "c_800": "0",
    "date_creation": "0000-00-00 00:00:00",
    "date_modification": "2019-01-29 12:23:57",
    "id_user_creation": null,
    "id_user_modification": "28",
    "price_old": "12.65700",
    "temps_auto": "0",
    "temps_manu": "0"
  }
]
